LICENSE.txt
MANIFEST.in
README.md
requirements.txt
setup.cfg
setup.py
confire/__init__.py
confire/config.py
confire/example.py
confire/exceptions.py
confire.egg-info/PKG-INFO
confire.egg-info/SOURCES.txt
confire.egg-info/dependency_links.txt
confire.egg-info/requires.txt
confire.egg-info/top_level.txt
confire.egg-info/zip-safe
docs/.DS_Store
docs/Makefile
docs/changelog.rst
docs/conf.py
docs/index.rst
docs/library.rst
docs/usage.rst
docs/figures/confits.jpg