Metadata-Version: 1.1
Name: confire
Version: 0.2.0
Summary: A simple app configuration scheme using YAML and class based defaults.
Home-page: https://github.com/bbengfort/confire
Author: Benjamin Bengfort
Author-email: benjamin@bengfort.com
License: MIT
Download-URL: https://github.com/bbengfort/confire/tarball/v0.2.0
Keywords: configuration,yaml,config,confire
Platform: UNKNOWN
Classifier: Development Status :: 4 - Beta
Classifier: Environment :: Console
Classifier: Intended Audience :: Developers
Classifier: License :: OSI Approved :: MIT License
Classifier: Natural Language :: English
Classifier: Operating System :: OS Independent
Classifier: Programming Language :: Python
Classifier: Programming Language :: Python :: 2.7
Classifier: Programming Language :: Python :: 3.3
Classifier: Topic :: Software Development
Classifier: Topic :: Software Development :: Libraries :: Python Modules
Classifier: Topic :: Utilities
